cab/__init__.py
cab/admin.py
cab/feeds.py
cab/forms.py
cab/listeners.py
cab/models.py
cab/search_indexes.py
cab/utils.py
cab/comments/__init__.py
cab/comments/forms.py
cab/migrations/0001_initial.py
cab/migrations/0002_migrate_ratings.py
cab/migrations/0003_remove_ratings_model.py
cab/migrations/0004_add_version_field.py
cab/migrations/0005_populate_version.py
cab/migrations/0006_add_flag.py
cab/migrations/0007_auto__del_field_snippet_django_version__add_field_snippet_version.py
cab/migrations/__init__.py
cab/static/img/feed-icon-10x10.png
cab/static/img/feed-icon-14x14.png
cab/static/js/snippets.js
cab/templates/cab/add_snippet.html
cab/templates/cab/confirm_bookmark_delete.html
cab/templates/cab/edit_snippet.html
cab/templates/cab/language_detail.html
cab/templates/cab/language_list.html
cab/templates/cab/most_bookmarked.html
cab/templates/cab/snippet_detail.html
cab/templates/cab/snippet_list.html
cab/templates/cab/tag_detail.html
cab/templates/cab/tag_list.html
cab/templates/cab/top_authors.html
cab/templates/cab/top_rated.html
cab/templates/cab/user_bookmarks.html
cab/templates/cab/user_detail.html
cab/templates/cab/user_list.html
cab/templates/cab/feeds/description.html
cab/templates/cab/feeds/title.html
cab/templates/search/indexes/cab/snippet_text.txt
cab/templatetags/__init__.py
cab/templatetags/cab_tags.py
cab/templatetags/core_tags.py
cab/templatetags/safe_markup.py
cab/urls/__init__.py
cab/urls/accounts.py
cab/urls/bookmarks.py
cab/urls/feeds.py
cab/urls/languages.py
cab/urls/popular.py
cab/urls/search.py
cab/urls/snippets.py
cab/urls/tags.py
cab/urls/users.py
cab/views/__init__.py
cab/views/accounts.py
cab/views/bookmarks.py
cab/views/languages.py
cab/views/popular.py
cab/views/snippets.py
django_cab-0.3.7.dist-info/DESCRIPTION.rst
django_cab-0.3.7.dist-info/METADATA
django_cab-0.3.7.dist-info/metadata.json
django_cab-0.3.7.dist-info/RECORD
django_cab-0.3.7.dist-info/top_level.txt
django_cab-0.3.7.dist-info/WHEEL
tests/__init__.py
tests/models.py
tests/requirements.txt
tests/search_sites.py
tests/settings.py
tests/tests.py
tests/urls.py
tests/templates/404.html
tests/templates/base.html
