Metadata-Version: 2.0
Name: django-cab
Version: 0.3.7
Summary: A code snippet manager, originally written to power djangosnippets.org
Home-page: http://github.com/django-de/django-cab
Author: James Bennett and contributors
Author-email: UNKNOWN
License: BSD
Platform: UNKNOWN
Classifier: Development Status :: 4 - Beta
Classifier: Environment :: Web Environment
Classifier: Intended Audience :: Developers
Classifier: License :: OSI Approved :: BSD License
Classifier: Operating System :: OS Independent
Classifier: Programming Language :: Python
Classifier: Framework :: Django
Requires-Dist: Markdown (>=2.2.1)
Requires-Dist: Pygments (>=1.6)
Requires-Dist: South (>=0.7.5)
Requires-Dist: akismet (>=0.2.0)
Requires-Dist: django-generic-aggregation (>=0.3.2)
Requires-Dist: django-simple-ratings (>=0.3.3)
Requires-Dist: django-haystack (>=2.1)
Requires-Dist: django-pagination (==1.0.7)
Requires-Dist: django-registration (==1.0)
Requires-Dist: django-taggit (==0.10)
Requires-Dist: django-comments-spamfighter (>=0.4)
Requires-Dist: django-recaptcha (>=1.0)
Requires-Dist: django-ratelimit-backend (==0.6.2)
